{"gameDetails":{"round":40,"maxRounds":400,"mapWidth":16,"mapHeight":8,"roundIncomeEnergy":5,"buildingPrices":{"ATTACK":30,"DEFENSE":30,"TESLA":100,"ENERGY":20},"buildingsStats":{"ATTACK":{"health":5,"constructionTime":1,"price":30,"weaponDamage":5,"weaponSpeed":2,"weaponCooldownPeriod":3,"energyGeneratedPerTurn":0,"destroyMultiplier":1,"constructionScore":4},"DEFENSE":{"health":20,"constructionTime":3,"price":30,"weaponDamage":0,"weaponSpeed":0,"weaponCooldownPeriod":0,"energyGeneratedPerTurn":0,"destroyMultiplier":1,"constructionScore":10},"TESLA":{"health":5,"constructionTime":10,"price":100,"weaponDamage":20,"weaponSpeed":0,"weaponCooldownPeriod":10,"energyGeneratedPerTurn":0,"destroyMultiplier":10,"constructionScore":20},"ENERGY":{"health":5,"constructionTime":1,"price":20,"weaponDamage":0,"weaponSpeed":0,"weaponCooldownPeriod":0,"energyGeneratedPerTurn":3,"destroyMultiplier":1,"constructionScore":3}},"ironCurtainStats":{"activeRounds":6,"resetPeriod":30,"price":100,"constructionScore":20}},"players":[{"playerType":"B","energy":16,"health":85,"hitsTaken":3,"score":616,"ironCurtainAvailable":true,"activeIronCurtainLifetime":-10,"isIronCurtainActive":false},{"playerType":"A","energy":105,"health":100,"hitsTaken":0,"score":1478,"ironCurtainAvailable":true,"activeIronCurtainLifetime":-10,"isIronCurtainActive":false}],"gameMap":[[{"x":0,"y":0,"buildings":[{"health":5,"constructionTimeLeft":-39,"price":20,"weaponDamage":0,"weaponSpeed":0,"weaponCooldownTimeLeft":0,"weaponCooldownPeriod":0,"destroyMultiplier":1,"constructionScore":3,"energyGeneratedPerTurn":3,"maxRange":0,"buildingType":"ENERGY","energyPerShot":0,"x":0,"y":0,"playerType":"A"}],"missiles":[],"cellOwner":"A"},{"x":1,"y":0,"buildings":[{"health":5,"constructionTimeLeft":-19,"price":30,"weaponDamage":5,"weaponSpeed":2,"weaponCooldownTimeLeft":1,"weaponCooldownPeriod":3,"destroyMultiplier":1,"constructionScore":4,"energyGeneratedPerTurn":0,"maxRange":0,"buildingType":"ATTACK","energyPerShot":0,"x":1,"y":0,"playerType":"A"}],"missiles":[],"cellOwner":"A"},{"x":2,"y":0,"buildings":[{"health":5,"constructionTimeLeft":-20,"price":30,"weaponDamage":5,"weaponSpeed":2,"weaponCooldownTimeLeft":0,"weaponCooldownPeriod":3,"destroyMultiplier":1,"constructionScore":4,"energyGeneratedPerTurn":0,"maxRange":0,"buildingType":"ATTACK","energyPerShot":0,"x":2,"y":0,"playerType":"A"}],"missiles":[],"cellOwner":"A"},{"x":3,"y":0,"buildings":[{"health":5,"constructionTimeLeft":-21,"price":30,"weaponDamage":5,"weaponSpeed":2,"weaponCooldownTimeLeft":3,"weaponCooldownPeriod":3,"destroyMultiplier":1,"constructionScore":4,"energyGeneratedPerTurn":0,"maxRange":0,"buildingType":"ATTACK","energyPerShot":0,"x":3,"y":0,"playerType":"A"}],"missiles":[],"cellOwner":"A"},{"x":4,"y":0,"buildings":[{"health":5,"constructionTimeLeft":-23,"price":30,"weaponDamage":5,"weaponSpeed":2,"weaponCooldownTimeLeft":1,"weaponCooldownPeriod":3,"destroyMultiplier":1,"constructionScore":4,"energyGeneratedPerTurn":0,"maxRange":0,"buildingType":"ATTACK","energyPerShot":0,"x":4,"y":0,"playerType":"A"}],"missiles":[],"cellOwner":"A"},{"x":5,"y":0,"buildings":[{"health":5,"constructionTimeLeft":-13,"price":30,"weaponDamage":5,"weaponSpeed":2,"weaponCooldownTimeLeft":3,"weaponCooldownPeriod":3,"destroyMultiplier":1,"constructionScore":4,"energyGeneratedPerTurn":0,"maxRange":0,"buildingType":"ATTACK","energyPerShot":0,"x":5,"y":0,"playerType":"A"}],"missiles":[{"damage":5,"speed":2,"id":"f735873c-4e1c-418a-acbb-cd938e480076","x":5,"y":0,"playerType":"A"}],"cellOwner":"A"},{"x":6,"y":0,"buildings":[],"missiles":[],"cellOwner":"A"},{"x":7,"y":0,"buildings":[],"missiles":[{"damage":5,"speed":2,"id":"2bdf2bcc-21a6-4fa2-82bd-3b5c7a4b8bf0","x":7,"y":0,"playerType":"A"},{"damage":5,"speed":2,"id":"37160dfa-c860-454c-95ed-4f370721214d","x":7,"y":0,"playerType":"A"}],"cellOwner":"A"},{"x":8,"y":0,"buildings":[],"missiles":[],"cellOwner":"B"},{"x":9,"y":0,"buildings":[],"missiles":[],"cellOwner":"B"},{"x":10,"y":0,"buildings":[],"missiles":[{"damage":5,"speed":2,"id":"2349d5db-8d14-4d01-8120-a42e06de6d9e","x":10,"y":0,"playerType":"A"},{"damage":5,"speed":2,"id":"022aa080-03c2-4444-84a2-be9e5cb171b2","x":10,"y":0,"playerType":"A"}],"cellOwner":"B"},{"x":11,"y":0,"buildings":[],"missiles":[],"cellOwner":"B"},{"x":12,"y":0,"buildings":[],"missiles":[],"cellOwner":"B"},{"x":13,"y":0,"buildings":[],"missiles":[{"damage":5,"speed":2,"id":"286d3865-d9ba-4706-b6a8-930bad3eb0f7","x":13,"y":0,"playerType":"A"}],"cellOwner":"B"},{"x":14,"y":0,"buildings":[],"missiles":[],"cellOwner":"B"},{"x":15,"y":0,"buildings":[],"missiles":[{"damage":5,"speed":2,"id":"87703500-83fb-4086-bcd4-00511de2cf25","x":15,"y":0,"playerType":"A"},{"damage":5,"speed":2,"id":"4910d31c-ea60-4fdc-923a-1e98ae312749","x":15,"y":0,"playerType":"A"}],"cellOwner":"B"}],[{"x":0,"y":1,"buildings":[{"health":5,"constructionTimeLeft":-36,"price":20,"weaponDamage":0,"weaponSpeed":0,"weaponCooldownTimeLeft":0,"weaponCooldownPeriod":0,"destroyMultiplier":1,"constructionScore":3,"energyGeneratedPerTurn":3,"maxRange":0,"buildingType":"ENERGY","energyPerShot":0,"x":0,"y":1,"playerType":"A"}],"missiles":[],"cellOwner":"A"},{"x":1,"y":1,"buildings":[{"health":5,"constructionTimeLeft":-9,"price":30,"weaponDamage":5,"weaponSpeed":2,"weaponCooldownTimeLeft":3,"weaponCooldownPeriod":3,"destroyMultiplier":1,"constructionScore":4,"energyGeneratedPerTurn":0,"maxRange":0,"buildingType":"ATTACK","energyPerShot":0,"x":1,"y":1,"playerType":"A"}],"missiles":[],"cellOwner":"A"},{"x":2,"y":1,"buildings":[],"missiles":[],"cellOwner":"A"},{"x":3,"y":1,"buildings":[],"missiles":[{"damage":5,"speed":2,"id":"fc7e5fe2-a271-4d6c-90f3-26df98244531","x":3,"y":1,"playerType":"A"}],"cellOwner":"A"},{"x":4,"y":1,"buildings":[],"missiles":[],"cellOwner":"A"},{"x":5,"y":1,"buildings":[],"missiles":[],"cellOwner":"A"},{"x":6,"y":1,"buildings":[],"missiles":[],"cellOwner":"A"},{"x":7,"y":1,"buildings":[],"missiles":[],"cellOwner":"A"},{"x":8,"y":1,"buildings":[],"missiles":[],"cellOwner":"B"},{"x":9,"y":1,"buildings":[],"missiles":[],"cellOwner":"B"},{"x":10,"y":1,"buildings":[],"missiles":[],"cellOwner":"B"},{"x":11,"y":1,"buildings":[],"missiles":[{"damage":5,"speed":2,"id":"e0df7437-850c-4c29-902d-4d0b8efbc4d1","x":11,"y":1,"playerType":"A"}],"cellOwner":"B"},{"x":12,"y":1,"buildings":[],"missiles":[],"cellOwner":"B"},{"x":13,"y":1,"buildings":[],"missiles":[],"cellOwner":"B"},{"x":14,"y":1,"buildings":[],"missiles":[],"cellOwner":"B"},{"x":15,"y":1,"buildings":[],"missiles":[],"cellOwner":"B"}],[{"x":0,"y":2,"buildings":[{"health":5,"constructionTimeLeft":-34,"price":20,"weaponDamage":0,"weaponSpeed":0,"weaponCooldownTimeLeft":0,"weaponCooldownPeriod":0,"destroyMultiplier":1,"constructionScore":3,"energyGeneratedPerTurn":3,"maxRange":0,"buildingType":"ENERGY","energyPerShot":0,"x":0,"y":2,"playerType":"A"}],"missiles":[],"cellOwner":"A"},{"x":1,"y":2,"buildings":[{"health":5,"constructionTimeLeft":-12,"price":30,"weaponDamage":5,"weaponSpeed":2,"weaponCooldownTimeLeft":0,"weaponCooldownPeriod":3,"destroyMultiplier":1,"constructionScore":4,"energyGeneratedPerTurn":0,"maxRange":0,"buildingType":"ATTACK","energyPerShot":0,"x":1,"y":2,"playerType":"A"}],"missiles":[],"cellOwner":"A"},{"x":2,"y":2,"buildings":[],"missiles":[],"cellOwner":"A"},{"x":3,"y":2,"buildings":[],"missiles":[],"cellOwner":"A"},{"x":4,"y":2,"buildings":[],"missiles":[],"cellOwner":"A"},{"x":5,"y":2,"buildings":[],"missiles":[],"cellOwner":"A"},{"x":6,"y":2,"buildings":[],"missiles":[],"cellOwner":"A"},{"x":7,"y":2,"buildings":[],"missiles":[],"cellOwner":"A"},{"x":8,"y":2,"buildings":[],"missiles":[],"cellOwner":"B"},{"x":9,"y":2,"buildings":[],"missiles":[{"damage":5,"speed":2,"id":"fe6a0c5e-e7c9-4842-b664-ea3f4741a07b","x":9,"y":2,"playerType":"A"}],"cellOwner":"B"},{"x":10,"y":2,"buildings":[{"health":10,"constructionTimeLeft":-9,"price":30,"weaponDamage":0,"weaponSpeed":0,"weaponCooldownTimeLeft":0,"weaponCooldownPeriod":0,"destroyMultiplier":1,"constructionScore":10,"energyGeneratedPerTurn":0,"maxRange":0,"buildingType":"DEFENSE","energyPerShot":0,"x":10,"y":2,"playerType":"B"}],"missiles":[],"cellOwner":"B"},{"x":11,"y":2,"buildings":[],"missiles":[],"cellOwner":"B"},{"x":12,"y":2,"buildings":[],"missiles":[],"cellOwner":"B"},{"x":13,"y":2,"buildings":[],"missiles":[],"cellOwner":"B"},{"x":14,"y":2,"buildings":[],"missiles":[],"cellOwner":"B"},{"x":15,"y":2,"buildings":[],"missiles":[],"cellOwner":"B"}],[{"x":0,"y":3,"buildings":[{"health":5,"constructionTimeLeft":-32,"price":20,"weaponDamage":0,"weaponSpeed":0,"weaponCooldownTimeLeft":0,"weaponCooldownPeriod":0,"destroyMultiplier":1,"constructionScore":3,"energyGeneratedPerTurn":3,"maxRange":0,"buildingType":"ENERGY","energyPerShot":0,"x":0,"y":3,"playerType":"A"}],"missiles":[],"cellOwner":"A"},{"x":1,"y":3,"buildings":[{"health":5,"constructionTimeLeft":-11,"price":30,"weaponDamage":5,"weaponSpeed":2,"weaponCooldownTimeLeft":1,"weaponCooldownPeriod":3,"destroyMultiplier":1,"constructionScore":4,"energyGeneratedPerTurn":0,"maxRange":0,"buildingType":"ATTACK","energyPerShot":0,"x":1,"y":3,"playerType":"A"}],"missiles":[],"cellOwner":"A"},{"x":2,"y":3,"buildings":[],"missiles":[],"cellOwner":"A"},{"x":3,"y":3,"buildings":[],"missiles":[],"cellOwner":"A"},{"x":4,"y":3,"buildings":[],"missiles":[],"cellOwner":"A"},{"x":5,"y":3,"buildings":[],"missiles":[],"cellOwner":"A"},{"x":6,"y":3,"buildings":[],"missiles":[],"cellOwner":"A"},{"x":7,"y":3,"buildings":[],"missiles":[{"damage":5,"speed":2,"id":"d44d9e6f-f4c3-4251-b1cc-b0eb05965098","x":7,"y":3,"playerType":"A"}],"cellOwner":"A"},{"x":8,"y":3,"buildings":[],"missiles":[],"cellOwner":"B"},{"x":9,"y":3,"buildings":[],"missiles":[],"cellOwner":"B"},{"x":10,"y":3,"buildings":[],"missiles":[],"cellOwner":"B"},{"x":11,"y":3,"buildings":[],"missiles":[],"cellOwner":"B"},{"x":12,"y":3,"buildings":[],"missiles":[],"cellOwner":"B"},{"x":13,"y":3,"buildings":[],"missiles":[],"cellOwner":"B"},{"x":14,"y":3,"buildings":[],"missiles":[],"cellOwner":"B"},{"x":15,"y":3,"buildings":[],"missiles":[{"damage":5,"speed":2,"id":"5615acfb-f20f-4b48-af4d-8fe0cc5dd1c6","x":15,"y":3,"playerType":"A"}],"cellOwner":"B"}],[{"x":0,"y":4,"buildings":[{"health":5,"constructionTimeLeft":-30,"price":20,"weaponDamage":0,"weaponSpeed":0,"weaponCooldownTimeLeft":0,"weaponCooldownPeriod":0,"destroyMultiplier":1,"constructionScore":3,"energyGeneratedPerTurn":3,"maxRange":0,"buildingType":"ENERGY","energyPerShot":0,"x":0,"y":4,"playerType":"A"}],"missiles":[],"cellOwner":"A"},{"x":1,"y":4,"buildings":[{"health":5,"constructionTimeLeft":-7,"price":30,"weaponDamage":5,"weaponSpeed":2,"weaponCooldownTimeLeft":1,"weaponCooldownPeriod":3,"destroyMultiplier":1,"constructionScore":4,"energyGeneratedPerTurn":0,"maxRange":0,"buildingType":"ATTACK","energyPerShot":0,"x":1,"y":4,"playerType":"A"}],"missiles":[],"cellOwner":"A"},{"x":2,"y":4,"buildings":[{"health":5,"constructionTimeLeft":0,"price":30,"weaponDamage":5,"weaponSpeed":2,"weaponCooldownTimeLeft":0,"weaponCooldownPeriod":3,"destroyMultiplier":1,"constructionScore":4,"energyGeneratedPerTurn":0,"maxRange":0,"buildingType":"ATTACK","energyPerShot":0,"x":2,"y":4,"playerType":"A"}],"missiles":[],"cellOwner":"A"},{"x":3,"y":4,"buildings":[{"health":5,"constructionTimeLeft":-1,"price":30,"weaponDamage":5,"weaponSpeed":2,"weaponCooldownTimeLeft":3,"weaponCooldownPeriod":3,"destroyMultiplier":1,"constructionScore":4,"energyGeneratedPerTurn":0,"maxRange":0,"buildingType":"ATTACK","energyPerShot":0,"x":3,"y":4,"playerType":"A"}],"missiles":[],"cellOwner":"A"},{"x":4,"y":4,"buildings":[{"health":5,"constructionTimeLeft":-2,"price":30,"weaponDamage":5,"weaponSpeed":2,"weaponCooldownTimeLeft":2,"weaponCooldownPeriod":3,"destroyMultiplier":1,"constructionScore":4,"energyGeneratedPerTurn":0,"maxRange":0,"buildingType":"ATTACK","energyPerShot":0,"x":4,"y":4,"playerType":"A"}],"missiles":[],"cellOwner":"A"},{"x":5,"y":4,"buildings":[{"health":5,"constructionTimeLeft":-3,"price":30,"weaponDamage":5,"weaponSpeed":2,"weaponCooldownTimeLeft":1,"weaponCooldownPeriod":3,"destroyMultiplier":1,"constructionScore":4,"energyGeneratedPerTurn":0,"maxRange":0,"buildingType":"ATTACK","energyPerShot":0,"x":5,"y":4,"playerType":"A"}],"missiles":[{"damage":5,"speed":2,"id":"f786a090-c833-49cf-b73a-ab8d5e607bea","x":5,"y":4,"playerType":"A"}],"cellOwner":"A"},{"x":6,"y":4,"buildings":[{"health":5,"constructionTimeLeft":-4,"price":30,"weaponDamage":5,"weaponSpeed":2,"weaponCooldownTimeLeft":0,"weaponCooldownPeriod":3,"destroyMultiplier":1,"constructionScore":4,"energyGeneratedPerTurn":0,"maxRange":0,"buildingType":"ATTACK","energyPerShot":0,"x":6,"y":4,"playerType":"A"}],"missiles":[],"cellOwner":"A"},{"x":7,"y":4,"buildings":[{"health":20,"constructionTimeLeft":-3,"price":30,"weaponDamage":0,"weaponSpeed":0,"weaponCooldownTimeLeft":0,"weaponCooldownPeriod":0,"destroyMultiplier":1,"constructionScore":10,"energyGeneratedPerTurn":0,"maxRange":0,"buildingType":"DEFENSE","energyPerShot":0,"x":7,"y":4,"playerType":"A"}],"missiles":[{"damage":5,"speed":2,"id":"fb628ead-1e26-4b74-ad8a-24a7b3578113","x":7,"y":4,"playerType":"A"}],"cellOwner":"A"},{"x":8,"y":4,"buildings":[],"missiles":[{"damage":5,"speed":2,"id":"ec2ca77d-baf6-43a4-8c88-1742684eca24","x":8,"y":4,"playerType":"A"}],"cellOwner":"B"},{"x":9,"y":4,"buildings":[],"missiles":[],"cellOwner":"B"},{"x":10,"y":4,"buildings":[],"missiles":[],"cellOwner":"B"},{"x":11,"y":4,"buildings":[],"missiles":[{"damage":5,"speed":2,"id":"2815c137-4219-41f4-b41b-1d7ea4733982","x":11,"y":4,"playerType":"A"}],"cellOwner":"B"},{"x":12,"y":4,"buildings":[],"missiles":[],"cellOwner":"B"},{"x":13,"y":4,"buildings":[],"missiles":[],"cellOwner":"B"},{"x":14,"y":4,"buildings":[{"health":5,"constructionTimeLeft":0,"price":20,"weaponDamage":0,"weaponSpeed":0,"weaponCooldownTimeLeft":0,"weaponCooldownPeriod":0,"destroyMultiplier":1,"constructionScore":3,"energyGeneratedPerTurn":3,"maxRange":0,"buildingType":"ENERGY","energyPerShot":0,"x":14,"y":4,"playerType":"B"}],"missiles":[{"damage":5,"speed":2,"id":"a8b8df55-bbd2-4d49-8acd-0594004755b4","x":14,"y":4,"playerType":"A"}],"cellOwner":"B"},{"x":15,"y":4,"buildings":[],"missiles":[],"cellOwner":"B"}],[{"x":0,"y":5,"buildings":[{"health":5,"constructionTimeLeft":-29,"price":20,"weaponDamage":0,"weaponSpeed":0,"weaponCooldownTimeLeft":0,"weaponCooldownPeriod":0,"destroyMultiplier":1,"constructionScore":3,"energyGeneratedPerTurn":3,"maxRange":0,"buildingType":"ENERGY","energyPerShot":0,"x":0,"y":5,"playerType":"A"}],"missiles":[],"cellOwner":"A"},{"x":1,"y":5,"buildings":[{"health":5,"constructionTimeLeft":-6,"price":30,"weaponDamage":5,"weaponSpeed":2,"weaponCooldownTimeLeft":2,"weaponCooldownPeriod":3,"destroyMultiplier":1,"constructionScore":4,"energyGeneratedPerTurn":0,"maxRange":0,"buildingType":"ATTACK","energyPerShot":0,"x":1,"y":5,"playerType":"A"}],"missiles":[],"cellOwner":"A"},{"x":2,"y":5,"buildings":[],"missiles":[],"cellOwner":"A"},{"x":3,"y":5,"buildings":[],"missiles":[],"cellOwner":"A"},{"x":4,"y":5,"buildings":[],"missiles":[],"cellOwner":"A"},{"x":5,"y":5,"buildings":[],"missiles":[{"damage":5,"speed":2,"id":"23bf2b91-5cbf-4f9f-9f4b-449d910b2265","x":5,"y":5,"playerType":"A"}],"cellOwner":"A"},{"x":6,"y":5,"buildings":[],"missiles":[],"cellOwner":"A"},{"x":7,"y":5,"buildings":[],"missiles":[],"cellOwner":"A"},{"x":8,"y":5,"buildings":[],"missiles":[],"cellOwner":"B"},{"x":9,"y":5,"buildings":[],"missiles":[],"cellOwner":"B"},{"x":10,"y":5,"buildings":[],"missiles":[],"cellOwner":"B"},{"x":11,"y":5,"buildings":[],"missiles":[],"cellOwner":"B"},{"x":12,"y":5,"buildings":[],"missiles":[],"cellOwner":"B"},{"x":13,"y":5,"buildings":[],"missiles":[{"damage":5,"speed":2,"id":"0da4e2c9-d4e9-432d-8c38-1492eca2b11c","x":13,"y":5,"playerType":"A"}],"cellOwner":"B"},{"x":14,"y":5,"buildings":[],"missiles":[],"cellOwner":"B"},{"x":15,"y":5,"buildings":[{"health":5,"constructionTimeLeft":-5,"price":20,"weaponDamage":0,"weaponSpeed":0,"weaponCooldownTimeLeft":0,"weaponCooldownPeriod":0,"destroyMultiplier":1,"constructionScore":3,"energyGeneratedPerTurn":3,"maxRange":0,"buildingType":"ENERGY","energyPerShot":0,"x":15,"y":5,"playerType":"B"}],"missiles":[],"cellOwner":"B"}],[{"x":0,"y":6,"buildings":[{"health":5,"constructionTimeLeft":-28,"price":20,"weaponDamage":0,"weaponSpeed":0,"weaponCooldownTimeLeft":0,"weaponCooldownPeriod":0,"destroyMultiplier":1,"constructionScore":3,"energyGeneratedPerTurn":3,"maxRange":0,"buildingType":"ENERGY","energyPerShot":0,"x":0,"y":6,"playerType":"A"}],"missiles":[],"cellOwner":"A"},{"x":1,"y":6,"buildings":[{"health":5,"constructionTimeLeft":-8,"price":30,"weaponDamage":5,"weaponSpeed":2,"weaponCooldownTimeLeft":0,"weaponCooldownPeriod":3,"destroyMultiplier":1,"constructionScore":4,"energyGeneratedPerTurn":0,"maxRange":0,"buildingType":"ATTACK","energyPerShot":0,"x":1,"y":6,"playerType":"A"}],"missiles":[],"cellOwner":"A"},{"x":2,"y":6,"buildings":[],"missiles":[],"cellOwner":"A"},{"x":3,"y":6,"buildings":[],"missiles":[],"cellOwner":"A"},{"x":4,"y":6,"buildings":[],"missiles":[],"cellOwner":"A"},{"x":5,"y":6,"buildings":[],"missiles":[],"cellOwner":"A"},{"x":6,"y":6,"buildings":[],"missiles":[],"cellOwner":"A"},{"x":7,"y":6,"buildings":[],"missiles":[],"cellOwner":"A"},{"x":8,"y":6,"buildings":[],"missiles":[],"cellOwner":"B"},{"x":9,"y":6,"buildings":[],"missiles":[{"damage":5,"speed":2,"id":"43c2a1c4-fa84-4ede-af6e-48eb771ff6ca","x":9,"y":6,"playerType":"A"}],"cellOwner":"B"},{"x":10,"y":6,"buildings":[{"health":15,"constructionTimeLeft":-5,"price":30,"weaponDamage":0,"weaponSpeed":0,"weaponCooldownTimeLeft":0,"weaponCooldownPeriod":0,"destroyMultiplier":1,"constructionScore":10,"energyGeneratedPerTurn":0,"maxRange":0,"buildingType":"DEFENSE","energyPerShot":0,"x":10,"y":6,"playerType":"B"}],"missiles":[],"cellOwner":"B"},{"x":11,"y":6,"buildings":[],"missiles":[],"cellOwner":"B"},{"x":12,"y":6,"buildings":[],"missiles":[],"cellOwner":"B"},{"x":13,"y":6,"buildings":[],"missiles":[],"cellOwner":"B"},{"x":14,"y":6,"buildings":[],"missiles":[],"cellOwner":"B"},{"x":15,"y":6,"buildings":[],"missiles":[],"cellOwner":"B"}],[{"x":0,"y":7,"buildings":[{"health":5,"constructionTimeLeft":-27,"price":20,"weaponDamage":0,"weaponSpeed":0,"weaponCooldownTimeLeft":0,"weaponCooldownPeriod":0,"destroyMultiplier":1,"constructionScore":3,"energyGeneratedPerTurn":3,"maxRange":0,"buildingType":"ENERGY","energyPerShot":0,"x":0,"y":7,"playerType":"A"}],"missiles":[],"cellOwner":"A"},{"x":1,"y":7,"buildings":[{"health":5,"constructionTimeLeft":-10,"price":30,"weaponDamage":5,"weaponSpeed":2,"weaponCooldownTimeLeft":2,"weaponCooldownPeriod":3,"destroyMultiplier":1,"constructionScore":4,"energyGeneratedPerTurn":0,"maxRange":0,"buildingType":"ATTACK","energyPerShot":0,"x":1,"y":7,"playerType":"A"}],"missiles":[],"cellOwner":"A"},{"x":2,"y":7,"buildings":[],"missiles":[],"cellOwner":"A"},{"x":3,"y":7,"buildings":[],"missiles":[],"cellOwner":"A"},{"x":4,"y":7,"buildings":[],"missiles":[],"cellOwner":"A"},{"x":5,"y":7,"buildings":[],"missiles":[{"damage":5,"speed":2,"id":"df18967b-abd2-4518-be3d-3ee4f7978de6","x":5,"y":7,"playerType":"A"}],"cellOwner":"A"},{"x":6,"y":7,"buildings":[],"missiles":[],"cellOwner":"A"},{"x":7,"y":7,"buildings":[],"missiles":[],"cellOwner":"A"},{"x":8,"y":7,"buildings":[],"missiles":[],"cellOwner":"B"},{"x":9,"y":7,"buildings":[],"missiles":[],"cellOwner":"B"},{"x":10,"y":7,"buildings":[{"health":20,"constructionTimeLeft":0,"price":30,"weaponDamage":0,"weaponSpeed":0,"weaponCooldownTimeLeft":0,"weaponCooldownPeriod":0,"destroyMultiplier":1,"constructionScore":10,"energyGeneratedPerTurn":0,"maxRange":0,"buildingType":"DEFENSE","energyPerShot":0,"x":10,"y":7,"playerType":"B"}],"missiles":[],"cellOwner":"B"},{"x":11,"y":7,"buildings":[],"missiles":[],"cellOwner":"B"},{"x":12,"y":7,"buildings":[],"missiles":[],"cellOwner":"B"},{"x":13,"y":7,"buildings":[],"missiles":[{"damage":5,"speed":2,"id":"44d4caa6-be6f-4e35-9c5a-5fcbd8457435","x":13,"y":7,"playerType":"A"}],"cellOwner":"B"},{"x":14,"y":7,"buildings":[],"missiles":[],"cellOwner":"B"},{"x":15,"y":7,"buildings":[],"missiles":[],"cellOwner":"B"}]],"teslaHitList":[],"ironCurtainHitList":[]}